[{"cinema":"SFC上影影城（永华店）","date":"2017-06-18","film":{"07厅":[{"show_time":"10:30","film_name":"盗信情缘","film_total_time":"110","director":"萨布","film_type_name":"剧情片"},{"show_time":"13:30","film_name":"哈吉布基的森林冒险","film_total_time":"76","director":"拉斯姆斯·A·西韦特","film_type_name":"动画片"},{"show_time":"18:30","film_name":"失控的生活","film_total_time":"103","director":"纳维德·达内施","film_type_name":"剧情片"},{"show_time":"20:45","film_name":"孔雀","film_total_time":"136","director":"顾长卫","film_type_name":"剧情片"}]}},{"cinema":"上海兰生典尚影院","date":"2017-06-18","film":{"06厅":[{"show_time":"15:45","film_name":"伦敦一家人","film_total_time":"95","director":"罗杰·梅因伍德","film_type_name":"动画片"},{"show_time":"18:30","film_name":"本能寺酒店","film_total_time":"119","director":"铃木雅之","film_type_name":"剧情片"}]}},{"cinema":"SFC上影影城（新衡山店）","date":"2017-06-18","film":{"01厅":[{"show_time":"09:00","film_name":"猫忍","film_total_time":"96","director":"渡边武","film_type_name":"剧情片"},{"show_time":"18:30","film_name":"愚行录","film_total_time":"120","director":"石川庆","film_type_name":"剧情片"},{"show_time":"20:45","film_name":"帝一之国","film_total_time":"118","director":"永井聪","film_type_name":"剧情片"}]}},{"cinema":"曹杨影城","date":"2017-06-18","film":{"01厅":[{"show_time":"13:30","film_name":"阿拉丁","film_total_time":"90","director":"罗恩·克莱门兹#约翰·马斯克","film_type_name":"动画片"},{"show_time":"15:45","film_name":"这个杀手不太冷 （4K）","film_total_time":"132","director":"吕克·贝松","film_type_name":"剧情片"},{"show_time":"18:30","film_name":"异形","film_total_time":"116","director":"雷德利·斯科特","film_type_name":"剧情片"},{"show_time":"20:45","film_name":"异形2","film_total_time":"138","director":"詹姆斯·卡梅隆","film_type_name":"剧情片"}]}},{"cinema":"上海和平影都","date":"2017-06-18","film":{"ATMOS厅":[{"show_time":"09:00","film_name":"宾虚（4K）","film_total_time":"212","director":"威廉·惠勒","film_type_name":"剧情片"},{"show_time":"13:30","film_name":"跑调天后","film_total_time":"111","director":"斯蒂芬·弗雷斯","film_type_name":"剧情片"},{"show_time":"15:45","film_name":"人生密密缝","film_total_time":"128","director":"荻上直子","film_type_name":"剧情片"},{"show_time":"18:30","film_name":"宣告黎明的露之歌","film_total_time":"112","director":"汤浅政明","film_type_name":"动画片"},{"show_time":"20:45","film_name":"空白的13年","film_total_time":"71","director":"斋藤工","film_type_name":"剧情片"}],"IMAX厅":[{"show_time":"20:45","film_name":"死侍 (IMAX)","film_total_time":"108","director":"提姆·米勒","film_type_name":"剧情片"}]}},{"cinema":"上海大光明电影院","date":"2017-06-18","film":{"01厅":[{"show_time":"08:30","film_name":"不干了，我开除了黑心公司","film_total_time":"114","director":"成岛出","film_type_name":"剧情片"},{"show_time":"10:30","film_name":"海边的生与死","film_total_time":"154","director":"越川道夫","film_type_name":"剧情片"},{"show_time":"13:30","film_name":"岗拉梅朵","film_total_time":"87","director":"扎西青朋","film_type_name":"纪录片"},{"show_time":"15:45","film_name":"会计刺客","film_total_time":"128","director":"加文·欧康诺","film_type_name":"动作片"},{"show_time":"18:30","film_name":"夜空总是最大密度的蓝色","film_total_time":"108","director":"石井裕也","film_type_name":"剧情片"},{"show_time":"20:45","film_name":"搏击俱乐部","film_total_time":"139","director":"大卫·芬奇","film_type_name":"剧情片"}],"02厅":[{"show_time":"10:30","film_name":"闪光少女","film_total_time":"100","director":"王冉","film_type_name":"剧情片"},{"show_time":"13:30","film_name":"少年犯","film_total_time":"101","director":"米凯莱·桑托罗","film_type_name":"纪录片"},{"show_time":"15:45","film_name":"有些怪胎","film_total_time":"97","director":"伊恩·麦卡利斯特·麦克唐纳","film_type_name":"剧情片"},{"show_time":"18:30","film_name":"努巴的心","film_total_time":"86","director":"肯尼斯·A·卡尔森","film_type_name":"纪录片"},{"show_time":"20:45","film_name":"悍女","film_total_time":"149","director":"马丁·库尔霍文","film_type_name":"剧情片"}],"03厅":[{"show_time":"13:30","film_name":"疟疾","film_total_time":"90","director":"帕维兹·沙巴兹","film_type_name":"剧情片"},{"show_time":"15:45","film_name":"胡说小镇","film_total_time":"82","director":"维特·荷默","film_type_name":"剧情片"},{"show_time":"20:45","film_name":"萨拉瓦库","film_total_time":"82","director":"普利塔基塔·阿莉安妮","film_type_name":"剧情片"}]}},{"cinema":"天山电影院-虹桥艺术中心旗舰店","date":"2017-06-18","film":{"剧院厅":[{"show_time":"18:30","film_name":"东京流浪汉","film_total_time":"83","director":"铃木清顺","film_type_name":"剧情片"},{"show_time":"20:45","film_name":"昼颜","film_total_time":"125","director":"西谷弘","film_type_name":"剧情片"}],"04厅":[{"show_time":"10:30","film_name":"白雪女王 3","film_total_time":"89","director":"阿列克谢·特斯蒂斯林","film_type_name":"动画片"},{"show_time":"13:30","film_name":"幻想曲 2000","film_total_time":"74","director":"皮克素特·亨特#保罗·布里齐","film_type_name":"动画片"},{"show_time":"15:45","film_name":"昼行闪耀的流星","film_total_time":"119","director":"新城毅彦","film_type_name":"剧情片"},{"show_time":"18:30","film_name":"卡麦拉之情","film_total_time":"81","director":"伊利亚·乌契杰利","film_type_name":"剧情片"},{"show_time":"20:45","film_name":"曼谷之夜","film_total_time":"183","director":"富田克也","film_type_name":"剧情片"}]}},{"cinema":"国泰电影院","date":"2017-06-18","film":{"02厅":[{"show_time":"15:45","film_name":"战争天堂","film_total_time":"132","director":"安德烈·康查洛夫斯基","film_type_name":"剧情片"},{"show_time":"18:30","film_name":"残影余像 （4K）","film_total_time":"100","director":"安杰依·瓦伊达","film_type_name":"剧情片"},{"show_time":"20:45","film_name":"午睡公主","film_total_time":"112","director":"神山健治","film_type_name":"动画片"}]}},{"cinema":"上影虹桥临空国际影城","date":"2017-06-18","film":{"06厅":[{"show_time":"15:45","film_name":"红粉惊魂","film_total_time":"136","director":"安鲁达·罗伊·乔杜","film_type_name":"剧情片"},{"show_time":"18:30","film_name":"早安秀","film_total_time":"104","director":"君塚良一","film_type_name":"剧情片"},{"show_time":"20:45","film_name":"依依惜别","film_total_time":"78","director":"纳维·马哈茂迪","film_type_name":"剧情片"}],"07厅":[{"show_time":"15:45","film_name":"婚事","film_total_time":"95","director":"斯蒂芬·斯特雷克","film_type_name":"剧情片"},{"show_time":"20:45","film_name":"我罩袍下的口红","film_total_time":"118","director":"阿兰克里塔·什里瓦斯","film_type_name":"剧情片"}]}},{"cinema":"四平电影院","date":"2017-06-18","film":{"01厅":[{"show_time":"13:30","film_name":"春&夏事件簿","film_total_time":"119","director":"市井昌秀","film_type_name":"剧情片"},{"show_time":"15:45","film_name":"好时光","film_total_time":"102","director":"本·萨弗迪#约书亚·萨弗迪","film_type_name":"剧情片"},{"show_time":"18:30","film_name":"追梦","film_total_time":"104","director":"萨米特·卡卡德","film_type_name":"剧情片"},{"show_time":"20:45","film_name":"起义者","film_total_time":"127","director":"佐尼特萨-索菲亚·波波奇切娃","film_type_name":"剧情片"}]}},{"cinema":"光影车间·静安店","date":"2017-06-18","film":{"01厅":[{"show_time":"13:30","film_name":"最后的呼吸","film_total_time":"73","director":"安娜贝尔·罗耀拉","film_type_name":"纪录片"},{"show_time":"15:45","film_name":"佛朗哥的遗产—西班牙的失窃儿童","film_total_time":"70","director":"因加·布雷默","film_type_name":"纪录片"},{"show_time":"18:30","film_name":"当保罗穿越大海","film_total_time":"97","director":"雅各布·普罗伊斯","film_type_name":"纪录片"},{"show_time":"20:45","film_name":"柏林叛逆高中","film_total_time":"93","director":"亚历山大·克雷德","film_type_name":"纪录片"}]}},{"cinema":"SFC上影影城（八佰伴店）","date":"2017-06-18","film":{"02厅":[{"show_time":"08:30","film_name":"陌生之地","film_total_time":"92","director":"哈什亚尔·莫斯塔法维","film_type_name":"剧情片"},{"show_time":"10:30","film_name":"嫌疑犯","film_total_time":"100","director":"斯库特·科克尔","film_type_name":"剧情片"},{"show_time":"13:30","film_name":"夫妻财产","film_total_time":"101","director":"乔克姆·拉弗塞","film_type_name":"剧情片"},{"show_time":"15:45","film_name":"还我河山","film_total_time":"130","director":"査特拉·维拉曼","film_type_name":"剧情片"},{"show_time":"18:30","film_name":"贾斯珀·琼斯","film_total_time":"101","director":"蕾切尔·帕金斯","film_type_name":"剧情片"},{"show_time":"20:45","film_name":"雪女","film_total_time":"97","director":"杉野希妃","film_type_name":"剧情片"}]}},{"cinema":"上海百丽宫影城（ifc商场店）","date":"2017-06-18","film":{"01厅":[{"show_time":"13:30","film_name":"风波再起","film_total_time":"115","director":"丹尼尔·迪马克","film_type_name":"剧情片"},{"show_time":"15:45","film_name":"第二个夏天，不再遇到你","film_total_time":"107","director":"中西健二","film_type_name":"剧情片"},{"show_time":"18:30","film_name":"我单纯的兄弟","film_total_time":"114","director":"马库斯·高勒","film_type_name":"剧情片"},{"show_time":"20:45","film_name":"阿德尔曼夫妇","film_total_time":"121","director":"尼古拉斯·贝多斯","film_type_name":"剧情片"}]}},{"cinema":"上海美琪大戏院","date":"2017-06-18","film":{"观众厅":[{"show_time":"20:45","film_name":"牛奶配送员的奇幻人生","film_total_time":"126","director":"埃米尔·库斯图里卡","film_type_name":"剧情片"}]}},{"cinema":"保利国际影城上海世博店","date":"2017-06-18","film":{"05厅":[{"show_time":"15:45","film_name":"与歌同行","film_total_time":"136","director":"詹姆斯·曼高德","film_type_name":"剧情片"},{"show_time":"18:30","film_name":"平衡","film_total_time":"84","director":"霍普·迪克森·利奇","film_type_name":"剧情片"},{"show_time":"20:45","film_name":"油墨滋味","film_total_time":"80","director":"摩根·西蒙","film_type_name":"剧情片"}]}},{"cinema":"AMG海上国际影城环球港店","date":"2017-06-18","film":{"07厅":[{"show_time":"15:45","film_name":"褐红","film_total_time":"95","director":"普尔克特","film_type_name":"剧情片"},{"show_time":"18:30","film_name":"大创业家","film_total_time":"116","director":"约翰·李·汉考克","film_type_name":"剧情片"}]}},{"cinema":"上海市沪北电影院","date":"2017-06-18","film":{"01厅":[{"show_time":"15:45","film_name":"隐藏人物","film_total_time":"127","director":"特奥多尔·梅尔菲","film_type_name":"剧情片"},{"show_time":"18:30","film_name":"搜索者","film_total_time":"119","director":"约翰·福特","film_type_name":"剧情片"}]}},{"cinema":"上海世纪友谊影城","date":"2017-06-18","film":{"06厅":[{"show_time":"10:30","film_name":"梅纳什","film_total_time":"83","director":"约书亚·温斯坦","film_type_name":"剧情片"},{"show_time":"13:30","film_name":"复仇记","film_total_time":"97","director":"帕托·特莱利亚","film_type_name":"剧情片"},{"show_time":"15:45","film_name":"怒火救援","film_total_time":"146","director":"托尼·斯科特","film_type_name":"剧情片"},{"show_time":"18:30","film_name":"父亲与伊藤先生","film_total_time":"119","director":"棚田由纪","film_type_name":"剧情片"},{"show_time":"20:45","film_name":"橡皮头 （4K）","film_total_time":"90","director":"大卫·林奇","film_type_name":"剧情片"}]}},{"cinema":"百美汇影城","date":"2017-06-18","film":{"01厅":[{"show_time":"13:30","film_name":"战地情爱","film_total_time":"107","director":"胡安·卡洛斯·韦索洛斯基","film_type_name":"剧情片"},{"show_time":"15:45","film_name":"文森特与世界的尽头","film_total_time":"122","director":"克里斯托弗·范·罗姆帕伊","film_type_name":"剧情片"},{"show_time":"18:30","film_name":"依依惜别","film_total_time":"78","director":"纳维·马哈茂迪","film_type_name":"剧情片"},{"show_time":"20:45","film_name":"暗房秘密","film_total_time":"132","director":"黑泽清","film_type_name":"剧情片"}]}},{"cinema":"上海宝山万达影城","date":"2017-06-18","film":{"10厅":[{"show_time":"13:30","film_name":"沉默 （4K）","film_total_time":"161","director":"马丁·斯科塞斯","film_type_name":"剧情片"},{"show_time":"15:45","film_name":"潜伏者","film_total_time":"127","director":"布拉德·福尔曼","film_type_name":"剧情片"},{"show_time":"18:30","film_name":"百日孤独","film_total_time":"96","director":"克里斯蒂安·帕斯夸列","film_type_name":"剧情片"},{"show_time":"20:45","film_name":"居里夫人","film_total_time":"100","director":"玛丽·诺埃尔","film_type_name":"剧情片"}]}},{"cinema":"SFC上影影城（金桥太茂店）","date":"2017-06-18","film":{"02厅":[{"show_time":"13:30","film_name":"爱，别，夏威夷","film_total_time":"93","director":"松村真吾","film_type_name":"剧情片"},{"show_time":"15:45","film_name":"一千根绳","film_total_time":"98","director":"图西·塔马西西","film_type_name":"剧情片"},{"show_time":"18:30","film_name":"妈咪的盒子","film_total_time":"89","director":"约翰尼·格林洛","film_type_name":"剧情片"},{"show_time":"20:45","film_name":"私人采购员","film_total_time":"105","director":"奥利维耶·阿萨亚斯","film_type_name":"剧情片"}]}},{"cinema":"上海开元地中海影城","date":"2017-06-18","film":{"02厅":[{"show_time":"18:30","film_name":"拯救萨莉","film_total_time":"94","director":"艾维德·莱恩戈恩","film_type_name":"动画片"},{"show_time":"20:45","film_name":"静默之下","film_total_time":"112","director":"萨哈尔·沙维特#埃雷兹·米兹拉希","film_type_name":"剧情片"}]}},{"cinema":"卢米埃上海紫荆影城","date":"2017-06-18","film":{"07厅":[{"show_time":"15:45","film_name":"相爱一天","film_total_time":"136","director":"班庄·比辛达拿刚","film_type_name":"剧情片"},{"show_time":"18:30","film_name":"我是马布里","film_total_time":"90","director":"杨子","film_type_name":"剧情片"}]}},{"cinema":"上海百丽宫影城（协信店）","date":"2017-06-18","film":{"01厅":[{"show_time":"13:30","film_name":"公园","film_total_time":"118","director":"濑田夏树","film_type_name":"剧情片"},{"show_time":"15:45","film_name":"滚烫的爱","film_total_time":"126","director":"中野量太","film_type_name":"剧情片"},{"show_time":"18:30","film_name":"白雪公主和七个小矮人","film_total_time":"83","director":"戴维·D·汉德","film_type_name":"动画片"},{"show_time":"20:45","film_name":"忽然之间","film_total_time":"112","director":"阿斯利·奥兹格","film_type_name":"剧情片"}]}},{"cinema":"上海星光影城（亚新旗舰店）","date":"2017-06-18","film":{"01厅":[{"show_time":"10:30","film_name":"放牛班的春天","film_total_time":"96","director":"克里斯托夫·巴拉蒂","film_type_name":"剧情片"},{"show_time":"13:30","film_name":"狮子王 （3D）","film_total_time":"89","director":"罗杰·阿勒斯#罗伯·明科夫","film_type_name":"动画片"},{"show_time":"15:45","film_name":"西北偏北（4K）","film_total_time":"137","director":"阿尔弗雷德·希区柯克","film_type_name":"剧情片"},{"show_time":"18:30","film_name":"危机72小时","film_total_time":"103","director":"亚历山大·卡萨特金","film_type_name":"剧情片"},{"show_time":"20:45","film_name":"夜色人生 （4K）","film_total_time":"129","director":"本·阿弗莱克","film_type_name":"剧情片"}]}},{"cinema":"星光映会影城（上海体育场店）","date":"2017-06-18","film":[]},{"cinema":"朵云轩杜比全景声影城","date":"2017-06-18","film":{"02厅":[{"show_time":"13:30","film_name":"囚禁","film_total_time":"82","director":"菲利普·范·莱乌","film_type_name":"剧情片"},{"show_time":"15:45","film_name":"雪峰神爸","film_total_time":"150","director":"阿贾耶·德乌干","film_type_name":"动作片"},{"show_time":"18:30","film_name":"欢迎来到德国","film_total_time":"117","director":"西蒙·范霍文","film_type_name":"剧情片"},{"show_time":"20:45","film_name":"幸福","film_total_time":"91","director":"萨布","film_type_name":"剧情片"}]}},{"cinema":"上海百丽宫影城（环贸iapm店）","date":"2017-06-18","film":{"06厅":[{"show_time":"13:30","film_name":"穿普拉达的女王","film_total_time":"110","director":"大卫·弗兰科尔","film_type_name":"剧情片"},{"show_time":"15:45","film_name":"突然20岁","film_total_time":"130","director":"阿利亚·西瑞汗","film_type_name":"剧情片"},{"show_time":"18:30","film_name":"酒会","film_total_time":"71","director":"莎莉·波特","film_type_name":"剧情片"},{"show_time":"20:45","film_name":"他们最好的","film_total_time":"117","director":"罗勒·莎菲","film_type_name":"剧情片"}]}},{"cinema":"星美正大影城","date":"2017-06-18","film":{"04厅":[{"show_time":"15:45","film_name":"绣春刀·修罗战场","film_total_time":"120","director":"路阳","film_type_name":"剧情片"},{"show_time":"18:30","film_name":"相棒剧场版4","film_total_time":"120","director":"桥本一","film_type_name":"剧情片"},{"show_time":"20:45","film_name":"兰在 1974","film_total_time":"82","director":"S.J. 奇罗","film_type_name":"剧情片"}]}},{"cinema":"SFC上影影城（百联又一城店）","date":"2017-06-18","film":{"05厅":[{"show_time":"13:30","film_name":"午夜开放","film_total_time":"97","director":"埃德瓦·贝耶","film_type_name":"剧情片"},{"show_time":"15:45","film_name":"恶魔蛙男","film_total_time":"132","director":"大友启史","film_type_name":"剧情片"},{"show_time":"18:30","film_name":"伤痕累累的恶魔","film_total_time":"98","director":"山岸圣太","film_type_name":"剧情片"},{"show_time":"20:45","film_name":"普罗米修斯","film_total_time":"123","director":"雷德利·斯科特","film_type_name":"剧情片"}]}},{"cinema":"上海百老汇影城（宝龙店）","date":"2017-06-18","film":{"Luxe厅":[{"show_time":"10:30","film_name":"一位著名的病人","film_total_time":"101","director":"朱利斯·舍夫契克","film_type_name":"剧情片"},{"show_time":"13:30","film_name":"杰出公民","film_total_time":"118","director":"加斯顿·杜普拉特#马里亚诺·寇恩","film_type_name":"剧情片"},{"show_time":"15:45","film_name":"英雄复英雄","film_total_time":"122","director":"宾·邦劳赖特#谭力·截禄冠","film_type_name":"动作片"},{"show_time":"18:30","film_name":"贝拉的奇幻花园","film_total_time":"93","director":"西蒙·阿布德","film_type_name":"剧情片"},{"show_time":"20:45","film_name":"地狱","film_total_time":"92","director":"斯戴芬·卢佐维茨基","film_type_name":"剧情片"}]}},{"cinema":"青浦大光明新国际影院","date":"2017-06-18","film":{"06厅":[{"show_time":"18:30","film_name":"佛朗哥的遗产—西班牙的失窃儿童","film_total_time":"70","director":"因加·布雷默","film_type_name":"纪录片"},{"show_time":"20:45","film_name":"衣柜里的猫","film_total_time":"82","director":"曾英庭","film_type_name":"剧情片"}]}},{"cinema":"大上海电影院","date":"2017-06-18","film":{"01厅":[{"show_time":"13:30","film_name":"维洛妮卡•佛斯","film_total_time":"104","director":"赖纳·维尔纳·法斯宾德","film_type_name":"剧情片"},{"show_time":"15:45","film_name":"寂寞芳心","film_total_time":"140","director":"赖纳·维尔纳·法斯宾德","film_type_name":"剧情片"},{"show_time":"18:30","film_name":"妄想的影帝","film_total_time":"83","director":"史蒂芬·库克森","film_type_name":"剧情片"},{"show_time":"20:45","film_name":"驾驶","film_total_time":"102","director":"萨布","film_type_name":"剧情片"}]}},{"cinema":"AMG海上明珠国际影城（莘庄店）","date":"2017-06-18","film":{"04厅":[{"show_time":"18:30","film_name":"濒临险境","film_total_time":"106","director":"赫里斯托·达马尔·阿拉姆","film_type_name":"剧情片"},{"show_time":"20:45","film_name":"意外","film_total_time":"89","director":"马汀·马利亚·斯密特","film_type_name":"剧情片"}]}},{"cinema":"上海UME新天地国际影城","date":"2017-06-18","film":{"01厅":[{"show_time":"13:30","film_name":"波兰当代经典动画合集","film_total_time":"106","director":"","film_type_name":"动画片"},{"show_time":"15:45","film_name":"流浪猫","film_total_time":"129","director":"榊英雄","film_type_name":"剧情片"},{"show_time":"18:30","film_name":"流浪巴黎","film_total_time":"82","director":"多米尼克·阿贝尔#菲欧娜·戈登","film_type_name":"剧情片"},{"show_time":"20:45","film_name":"生在幼子","film_total_time":"128","director":"三岛有纪子","film_type_name":"剧情片"}]}},{"cinema":"嘉定影剧院","date":"2017-06-18","film":{"03厅":[{"show_time":"13:30","film_name":"小鸟总动员","film_total_time":"84","director":"托比·格恩柯尔#雷扎·梅马里","film_type_name":"动画片"},{"show_time":"15:45","film_name":"春宵苦短，少女前进吧！","film_total_time":"93","director":"汤浅政明","film_type_name":"动画片"},{"show_time":"18:30","film_name":"家族之苦2","film_total_time":"114","director":"山田洋次","film_type_name":"剧情片"},{"show_time":"20:45","film_name":"自杀小队","film_total_time":"123","director":"大卫·阿耶","film_type_name":"动作片"}]}},{"cinema":"华士达影城（徐汇店）","date":"2017-06-18","film":{"05厅":[{"show_time":"13:30","film_name":"秘密特工（3D）","film_total_time":"83","director":"罗德里戈·艾巴#塞莉亚·卡通达#基戈·米斯特罗里戈","film_type_name":"动画片"},{"show_time":"15:45","film_name":"声音猎人","film_total_time":"89","director":"丹尼兹·辛纳","film_type_name":"剧情片"},{"show_time":"18:30","film_name":"爱情与友谊","film_total_time":"90","director":"惠特·斯蒂尔曼","film_type_name":"剧情片"},{"show_time":"20:45","film_name":"最后的居民","film_total_time":"83","director":"吉文·阿维蒂西恩","film_type_name":"剧情片"}]}},{"cinema":"兰馨·悦立方影城","date":"2017-06-18","film":{"04厅":[{"show_time":"15:45","film_name":"燕子号与亚马逊号","film_total_time":"98","director":"菲莉帕·洛索普","film_type_name":"剧情片"},{"show_time":"18:30","film_name":"幸福在西方","film_total_time":"102","director":"克里斯蒂安·蒙吉","film_type_name":"剧情片"}]}},{"cinema":"上岸影城（金山店）","date":"2017-06-18","film":{"02厅":[{"show_time":"18:30","film_name":"A计划","film_total_time":"106","director":"成龙#洪金宝","film_type_name":"剧情片"}]}},{"cinema":"SFC上影影城（南桥百联店）","date":"2017-06-18","film":{"05厅":[{"show_time":"18:30","film_name":"疟疾","film_total_time":"90","director":"帕维兹·沙巴兹","film_type_name":"剧情片"},{"show_time":"20:45","film_name":"静默之下","film_total_time":"112","director":"萨哈尔·沙维特#埃雷兹·米兹拉希","film_type_name":"剧情片"}]}},{"cinema":"SFC上影影城（喜玛拉雅店）","date":"2017-06-18","film":{"04厅":[{"show_time":"18:30","film_name":"被诅咒的普丁","film_total_time":"95","director":"卡尔·勒米厄","film_type_name":"剧情片"},{"show_time":"20:45","film_name":"摔跤手苏丹","film_total_time":"170","director":"阿里·阿巴斯·萨法尔","film_type_name":"动作片"}]}},{"cinema":"金逸影城上海虹口龙之梦IMAX店","date":"2017-06-18","film":{"01厅":[{"show_time":"18:30","film_name":"故障状况","film_total_time":"111","director":"克特林·萨伊泽斯库","film_type_name":"剧情片"},{"show_time":"20:45","film_name":"同步","film_total_time":"84","director":"万田邦敏","film_type_name":"剧情片"}]}},{"cinema":"SFC上影影城（美罗城店）","date":"2017-06-18","film":{"01厅":[{"show_time":"13:30","film_name":"白蚁","film_total_time":"96","director":"朱贤哲","film_type_name":"剧情片"},{"show_time":"15:45","film_name":"乱莺","film_total_time":"134","director":"出海拓治","film_type_name":"剧情片"},{"show_time":"18:30","film_name":"艾娃","film_total_time":"89","director":"萨宾·纳拉斯","film_type_name":"剧情片"},{"show_time":"20:45","film_name":"墙里的声音","film_total_time":"95","director":"艾瑞克·D·豪威尔","film_type_name":"剧情片"}]}},{"cinema":"SFC上海影城","date":"2017-06-18","film":{"01厅":[{"show_time":"09:00","film_name":"七武士 （4K）","film_total_time":"207","director":"黑泽明","film_type_name":"剧情片"},{"show_time":"13:30","film_name":"明月几时有","film_total_time":"130","director":"许鞍华","film_type_name":"剧情片"},{"show_time":"16:15","film_name":"天梯:蔡国强的艺术","film_total_time":"74","director":"凯文·麦克唐纳","film_type_name":"纪录片"},{"show_time":"18:30","film_name":"比海更深","film_total_time":"118","director":"是枝裕和","film_type_name":"剧情片"},{"show_time":"20:45","film_name":"3月的狮子 后篇","film_total_time":"140","director":"大友启史","film_type_name":"剧情片"}],"02厅":[{"show_time":"08:30","film_name":"流浪猫鲍勃","film_total_time":"103","director":"罗杰·斯波蒂斯伍德","film_type_name":"剧情片"},{"show_time":"10:30","film_name":"真田十勇士","film_total_time":"134","director":"堤幸彦","film_type_name":"剧情片"},{"show_time":"13:30","film_name":"摇摇晃晃的人间","film_total_time":"89","director":"范俭","film_type_name":"纪录片"},{"show_time":"15:45","film_name":"疯癫之翼","film_total_time":"106","director":"罗伯特·穆兰","film_type_name":"剧情片"},{"show_time":"18:30","film_name":"冷酷的心","film_total_time":"120","director":"约翰内斯·纳贝","film_type_name":"剧情片"},{"show_time":"20:45","film_name":"月光男孩","film_total_time":"111","director":"巴里·詹金斯","film_type_name":"剧情片"}],"03厅":[{"show_time":"08:30","film_name":"血浓于罪","film_total_time":"100","director":"亚当·史密斯","film_type_name":"剧情片"},{"show_time":"10:30","film_name":"至爱梵高","film_total_time":"95","director":"多洛塔·科别拉#休·韦尔什曼","film_type_name":"动画片"},{"show_time":"13:30","film_name":"龙之战","film_total_time":"116","director":"高峰","film_type_name":"剧情片"},{"show_time":"15:45","film_name":"闪光少女","film_total_time":"100","director":"王冉","film_type_name":"剧情片"},{"show_time":"18:30","film_name":"东京风之交响乐团","film_total_time":"75","director":"坂下雄一郎","film_type_name":"剧情片"},{"show_time":"20:45","film_name":"强尼·凯克","film_total_time":"105","director":"黄熙","film_type_name":"剧情片"}],"07厅":[{"show_time":"10:30","film_name":"归去","film_total_time":"102","director":"颜雷","film_type_name":"剧情片"},{"show_time":"13:30","film_name":"冬天里","film_total_time":"98","director":"彭士刚","film_type_name":"剧情片"},{"show_time":"15:45","film_name":"七儿娘","film_total_time":"90","director":"牛建荣#牛牛","film_type_name":"剧情片"},{"show_time":"18:30","film_name":"末日救赎","film_total_time":"91","director":"谢添","film_type_name":"剧情片"},{"show_time":"20:45","film_name":"八月","film_total_time":"107","director":"张大磊","film_type_name":"剧情片"}]}}]